MANIFEST.in
README.md
requirements.txt
setup.py
blueqat_classicalbit_backend/__init__.py
blueqat_classicalbit_backend/__main__.py
blueqat_classicalbit_backend.egg-info/PKG-INFO
blueqat_classicalbit_backend.egg-info/SOURCES.txt
blueqat_classicalbit_backend.egg-info/dependency_links.txt
blueqat_classicalbit_backend.egg-info/requires.txt
blueqat_classicalbit_backend.egg-info/top_level.txt